Workbook

Sheet Summary
A1: Estimate Master — New Features: Hours Summary
A2: Totals update from the Hours Breakdown sheet. Change Include? there to test a smaller scope.
A3: Hours filled 30 Sep 2026 as a planning estimate (±20%) for dev-lead review. Status column updated: all 14 features are now in the clickable prototype.
A4: Feature | B4: Name | C4: Depends on | D4: Core hours | E4: Optional hours | F4: Full scope | G4: Selected hours | H4: Hours saved | I4: Prototype status | J4: Build wave
A5: 3 | B5: Project-Specific Color Card | C5: — | D5: =SUMIFS('Hours Breakdown'!$G$5:$G$300,'Hours Breakdown'!$A$5:$A$300,A5,'Hours Breakdown'!$E$5:$E$300,"Core") -> 144 | E5: =SUMIFS('Hours Breakdown'!$G$5:$G$300,'Hours Breakdown'!$A$5:$A$300,A5,'Hours Breakdown'!$E$5:$E$300,"Optional") -> 48 | F5: =D5+E5 -> 192 | G5: =SUMIFS('Hours Breakdown'!$I$5:$I$300,'Hours Breakdown'!$A$5:$A$300,A5) -> 192 | H5: =F5-G5 -> 0 | I5: In prototype | J5: Wave 1
A6: 18 | B6: Material Calculation And Order Generation | C6: 3 | D6: =SUMIFS('Hours Breakdown'!$G$5:$G$300,'Hours Breakdown'!$A$5:$A$300,A6,'Hours Breakdown'!$E$5:$E$300,"Core") -> 160 | E6: =SUMIFS('Hours Breakdown'!$G$5:$G$300,'Hours Breakdown'!$A$5:$A$300,A6,'Hours Breakdown'!$E$5:$E$300,"Optional") -> 100 | F6: =D6+E6 -> 260 | G6: =SUMIFS('Hours Breakdown'!$I$5:$I$300,'Hours Breakdown'!$A$5:$A$300,A6) -> 260 | H6: =F6-G6 -> 0 | I6: In prototype | J6: Wave 1
A7: 19 | B7: Supplier Integration | C7: 18 | D7: =SUMIFS('Hours Breakdown'!$G$5:$G$300,'Hours Breakdown'!$A$5:$A$300,A7,'Hours Breakdown'!$E$5:$E$300,"Core") -> 104 | E7: =SUMIFS('Hours Breakdown'!$G$5:$G$300,'Hours Breakdown'!$A$5:$A$300,A7,'Hours Breakdown'!$E$5:$E$300,"Optional") -> 88 | F7: =D7+E7 -> 192 | G7: =SUMIFS('Hours Breakdown'!$I$5:$I$300,'Hours Breakdown'!$A$5:$A$300,A7) -> 192 | H7: =F7-G7 -> 0 | I7: In prototype | J7: Wave 1
A8: 21 | B8: Estimated Versus Actual Performance | C8: 22, 24, 33 | D8: =SUMIFS('Hours Breakdown'!$G$5:$G$300,'Hours Breakdown'!$A$5:$A$300,A8,'Hours Breakdown'!$E$5:$E$300,"Core") -> 80 | E8: =SUMIFS('Hours Breakdown'!$G$5:$G$300,'Hours Breakdown'!$A$5:$A$300,A8,'Hours Breakdown'!$E$5:$E$300,"Optional") -> 64 | F8: =D8+E8 -> 144 | G8: =SUMIFS('Hours Breakdown'!$I$5:$I$300,'Hours Breakdown'!$A$5:$A$300,A8) -> 144 | H8: =F8-G8 -> 0 | I8: In prototype | J8: Wave 4
A9: 22 | B9: Employee Hours And Payroll | C9: — | D9: =SUMIFS('Hours Breakdown'!$G$5:$G$300,'Hours Breakdown'!$A$5:$A$300,A9,'Hours Breakdown'!$E$5:$E$300,"Core") -> 184 | E9: =SUMIFS('Hours Breakdown'!$G$5:$G$300,'Hours Breakdown'!$A$5:$A$300,A9,'Hours Breakdown'!$E$5:$E$300,"Optional") -> 72 | F9: =D9+E9 -> 256 | G9: =SUMIFS('Hours Breakdown'!$I$5:$I$300,'Hours Breakdown'!$A$5:$A$300,A9) -> 256 | H9: =F9-G9 -> 0 | I9: In prototype | J9: Wave 3
A10: 24 | B10: Change Orders And Additional Work | C10: 3, 18 | D10: =SUMIFS('Hours Breakdown'!$G$5:$G$300,'Hours Breakdown'!$A$5:$A$300,A10,'Hours Breakdown'!$E$5:$E$300,"Core") -> 136 | E10: =SUMIFS('Hours Breakdown'!$G$5:$G$300,'Hours Breakdown'!$A$5:$A$300,A10,'Hours Breakdown'!$E$5:$E$300,"Optional") -> 96 | F10: =D10+E10 -> 232 | G10: =SUMIFS('Hours Breakdown'!$I$5:$I$300,'Hours Breakdown'!$A$5:$A$300,A10) -> 232 | H10: =F10-G10 -> 0 | I10: In prototype | J10: Wave 1
A11: 25 | B11: Historical Property Paint Record | C11: 3 | D11: =SUMIFS('Hours Breakdown'!$G$5:$G$300,'Hours Breakdown'!$A$5:$A$300,A11,'Hours Breakdown'!$E$5:$E$300,"Core") -> 128 | E11: =SUMIFS('Hours Breakdown'!$G$5:$G$300,'Hours Breakdown'!$A$5:$A$300,A11,'Hours Breakdown'!$E$5:$E$300,"Optional") -> 148 | F11: =D11+E11 -> 276 | G11: =SUMIFS('Hours Breakdown'!$I$5:$I$300,'Hours Breakdown'!$A$5:$A$300,A11) -> 276 | H11: =F11-G11 -> 0 | I11: In prototype | J11: Wave 2
A12: 26 | B12: Customer QR Paint Record | C12: 25 | D12: =SUMIFS('Hours Breakdown'!$G$5:$G$300,'Hours Breakdown'!$A$5:$A$300,A12,'Hours Breakdown'!$E$5:$E$300,"Core") -> 52 | E12: =SUMIFS('Hours Breakdown'!$G$5:$G$300,'Hours Breakdown'!$A$5:$A$300,A12,'Hours Breakdown'!$E$5:$E$300,"Optional") -> 76 | F12: =D12+E12 -> 128 | G12: =SUMIFS('Hours Breakdown'!$I$5:$I$300,'Hours Breakdown'!$A$5:$A$300,A12) -> 128 | H12: =F12-G12 -> 0 | I12: In prototype | J12: Wave 2
A13: 27 | B13: Paint Life And Automated Repainting Alerts | C13: 25 | D13: =SUMIFS('Hours Breakdown'!$G$5:$G$300,'Hours Breakdown'!$A$5:$A$300,A13,'Hours Breakdown'!$E$5:$E$300,"Core") -> 100 | E13: =SUMIFS('Hours Breakdown'!$G$5:$G$300,'Hours Breakdown'!$A$5:$A$300,A13,'Hours Breakdown'!$E$5:$E$300,"Optional") -> 58 | F13: =D13+E13 -> 158 | G13: =SUMIFS('Hours Breakdown'!$I$5:$I$300,'Hours Breakdown'!$A$5:$A$300,A13) -> 158 | H13: =F13-G13 -> 0 | I13: In prototype | J13: Wave 2
A14: 28 | B14: Future Estimating And Reordering | C14: 25 | D14: =SUMIFS('Hours Breakdown'!$G$5:$G$300,'Hours Breakdown'!$A$5:$A$300,A14,'Hours Breakdown'!$E$5:$E$300,"Core") -> 88 | E14: =SUMIFS('Hours Breakdown'!$G$5:$G$300,'Hours Breakdown'!$A$5:$A$300,A14,'Hours Breakdown'!$E$5:$E$300,"Optional") -> 76 | F14: =D14+E14 -> 164 | G14: =SUMIFS('Hours Breakdown'!$I$5:$I$300,'Hours Breakdown'!$A$5:$A$300,A14) -> 164 | H14: =F14-G14 -> 0 | I14: In prototype | J14: Wave 2
A15: 29 | B15: Repainting Follow-Up Workflow | C15: 27 | D15: =SUMIFS('Hours Breakdown'!$G$5:$G$300,'Hours Breakdown'!$A$5:$A$300,A15,'Hours Breakdown'!$E$5:$E$300,"Core") -> 76 | E15: =SUMIFS('Hours Breakdown'!$G$5:$G$300,'Hours Breakdown'!$A$5:$A$300,A15,'Hours Breakdown'!$E$5:$E$300,"Optional") -> 88 | F15: =D15+E15 -> 164 | G15: =SUMIFS('Hours Breakdown'!$I$5:$I$300,'Hours Breakdown'!$A$5:$A$300,A15) -> 164 | H15: =F15-G15 -> 0 | I15: In prototype | J15: Wave 2
A16: 30 | B16: Estimating Performance Feedback | C16: 21, 22 | D16: =SUMIFS('Hours Breakdown'!$G$5:$G$300,'Hours Breakdown'!$A$5:$A$300,A16,'Hours Breakdown'!$E$5:$E$300,"Core") -> 80 | E16: =SUMIFS('Hours Breakdown'!$G$5:$G$300,'Hours Breakdown'!$A$5:$A$300,A16,'Hours Breakdown'!$E$5:$E$300,"Optional") -> 60 | F16: =D16+E16 -> 140 | G16: =SUMIFS('Hours Breakdown'!$I$5:$I$300,'Hours Breakdown'!$A$5:$A$300,A16) -> 140 | H16: =F16-G16 -> 0 | I16: In prototype | J16: Wave 4
... A18: 34 | B18: Social Media And Marketing Management | C18: 25 | D18: =SUMIFS('Hours Breakdown'!$G$5:$G$300,'Hours Breakdown'!$A$5:$A$300,A18,'Hours Breakdown'!$E$5:$E$300,"Core") -> 128 | E18: =SUMIFS('Hours Breakdown'!$G$5:$G$300,'Hours Breakdown'!$A$5:$A$300,A18,'Hours Breakdown'!$E$5:$E$300,"Optional") -> 96 | F18: =D18+E18 -> 224 | G18: =SUMIFS('Hours Breakdown'!$I$5:$I$300,'Hours Breakdown'!$A$5:$A$300,A18) -> 224 | H18: =F18-G18 -> 0 | I18: In prototype | J18: Wave 4
B19: Total, all 14 features | D19: =SUM(D5:D18) -> 1636 | E19: =SUM(E5:E18) -> 1142 | F19: =SUM(F5:F18) -> 2778 | G19: =SUM(G5:G18) -> 2778 | H19: =SUM(H5:H18) -> 0
A21: How to read this
A22: Core hours: the minimum build that makes the feature work as the design intends. These rows cannot be removed.
A23: Optional hours: functions the client can leave out. Each feature still works without them; the 'If left out' column says what changes.
A24: Selected hours: the hours for the current choices on the Hours Breakdown sheet. Hours saved = Full scope minus Selected.
A25: Depends on: features that should be built first, or whose data this feature uses. Removing a whole feature affects the features that depend on it.
A26: Prototype status: whether the feature is in the clickable prototype. It does not mean the production build has started.
A28: Recommended add-ons (not in the 14 — client to confirm)
A29: Feature | B29: Name | C29: Depends on | D29: Full hours | G29: Selected hours | I29: Status
A30: 15 | B30: Changing Labor Requirements | C30: 14 (live scheduler) | D30: =SUMIFS('Hours Breakdown'!$G$232:$G$300,'Hours Breakdown'!$A$232:$A$300,A30) -> 16 | G30: =SUMIFS('Hours Breakdown'!$I$232:$I$300,'Hours Breakdown'!$A$232:$A$300,A30) -> 0 | I30: Not in prototype | J30: Wave 1
A31: 16 | B31: Weather And Production Disruptions | C31: 14 | D31: =SUMIFS('Hours Breakdown'!$G$232:$G$300,'Hours Breakdown'!$A$232:$A$300,A31) -> 40 | G31: =SUMIFS('Hours Breakdown'!$I$232:$I$300,'Hours Breakdown'!$A$232:$A$300,A31) -> 0 | I31: Partly in prototype | J31: Wave 1
A32: 17 | B32: Protected Jobs And Leapfrog Rescheduling | C32: 16 | D32: =SUMIFS('Hours Breakdown'!$G$232:$G$300,'Hours Breakdown'!$A$232:$A$300,A32) -> 32 | G32: =SUMIFS('Hours Breakdown'!$I$232:$I$300,'Hours Breakdown'!$A$232:$A$300,A32) -> 0 | I32: Partly in prototype | J32: Wave 1
A33: 20 | B33: Production And Actual Project Record | C33: 13, 22 | D33: =SUMIFS('Hours Breakdown'!$G$232:$G$300,'Hours Breakdown'!$A$232:$A$300,A33) -> 32 | G33: =SUMIFS('Hours Breakdown'!$I$232:$I$300,'Hours Breakdown'!$A$232:$A$300,A33) -> 0 | I33: Partly in prototype | J33: Wave 2
B34: Total, add-ons | D34: =SUM(D30:D33) -> 120 | G34: =SUM(G30:G33) -> 0
B36: GRAND TOTAL development hours (14 features + selected add-ons) | G36: =G19+G34 -> 2778

Sheet Timeline & Cost
A1: Estimate Master — Delivery Timeline and Cost
A2: Blue text in yellow cells = inputs you can change. Everything else is calculated from the Summary sheet.
A4: Inputs
A5: Kickoff date (after approval + signed SOW) | B5: 46314
A6: Developers on the build | B6: 3
A7: Productive dev hours per developer per week | B7: 32
A8: QA effort (% of dev hours) | B8: 0.2
A9: Project management (% of dev hours) | B9: 0.1
A10: UAT, deployment and handover (fixed hours) | B10: 80
A11: UAT window after the last wave (weeks) | B11: 2
A12: Blended hourly rate (USD) — enter before quoting | C12: Leave blank until the rate is agreed; cost cells show "Enter rate".
A14: Team capacity (dev hours per week) | B14: =B6*B7 -> 96
A16: Wave | B16: Features | C16: What the client gets | D16: Dev hours (selected) | E16: QA + PM hours | F16: Total hours | G16: Weeks | H16: Start | I16: End | J16: Cost (USD)
A17: Wave 1 | B17: 3, 18, 19, 24 (+15, 16, 17 if added) | C17: Paint spec → purchase orders → supplier → change orders | D17: =SUMIFS(Summary!$G$5:$G$18,Summary!$J$5:$J$18,A17)+SUMIFS(Summary!$G$30:$G$33,Summary!$J$30:$J$33,A17) -> 876 | E17: =ROUND(D17*($B$8+$B$9),0) -> 263 | F17: =D17+E17 -> 1139 | G17: =IF(D17=0,0,ROUNDUP(D17/$B$14,0)) -> 10 | H17: =B5 -> 46314 | I17: =H17+G17*7 -> 46384 | J17: =IF($B$12="","Enter rate",F17*$B$12) -> Enter rate
A18: Wave 2 | B18: 25, 26, 27, 28, 29 (+20 if added) | C18: Property paint record, customer QR, repaint alerts, repeat estimates, follow-ups | D18: =SUMIFS(Summary!$G$5:$G$18,Summary!$J$5:$J$18,A18)+SUMIFS(Summary!$G$30:$G$33,Summary!$J$30:$J$33,A18) -> 890 | E18: =ROUND(D18*($B$8+$B$9),0) -> 267 | F18: =D18+E18 -> 1157 | G18: =IF(D18=0,0,ROUNDUP(D18/$B$14,0)) -> 10 | H18: =I17 -> 46384 | I18: =H18+G18*7 -> 46454 | J18: =IF($B$12="","Enter rate",F18*$B$12) -> Enter rate
A19: Wave 3 | B19: 22, 33 | C19: Crew clock, timesheets & Gusto export; QuickBooks finance | D19: =SUMIFS(Summary!$G$5:$G$18,Summary!$J$5:$J$18,A19)+SUMIFS(Summary!$G$30:$G$33,Summary!$J$30:$J$33,A19) -> 504 | E19: =ROUND(D19*($B$8+$B$9),0) -> 151 | F19: =D19+E19 -> 655 | G19: =IF(D19=0,0,ROUNDUP(D19/$B$14,0)) -> 6 | H19: =I18 -> 46454 | I19: =H19+G19*7 -> 46496 | J19: =IF($B$12="","Enter rate",F19*$B$12) -> Enter rate
A20: Wave 4 | B20: 21, 30, 34 | C20: Estimated vs actual, rate feedback, social media & website leads | D20: =SUMIFS(Summary!$G$5:$G$18,Summary!$J$5:$J$18,A20)+SUMIFS(Summary!$G$30:$G$33,Summary!$J$30:$J$33,A20) -> 508 | E20: =ROUND(D20*($B$8+$B$9),0) -> 152 | F20: =D20+E20 -> 660 | G20: =IF(D20=0,0,ROUNDUP(D20/$B$14,0)) -> 6 | H20: =I19 -> 46496 | I20: =H20+G20*7 -> 46538 | J20: =IF($B$12="","Enter rate",F20*$B$12) -> Enter rate
A21: UAT & go-live | C21: Client testing, fixes, deployment, training & handover | E21: =B10 -> 80 | F21: =E21 -> 80 | G21: =B11 -> 2 | H21: =I20 -> 46538 | I21: =H21+G21*7 -> 46552 | J21: =IF($B$12="","Enter rate",F21*$B$12) -> Enter rate
A22: TOTAL | D22: =SUM(D17:D21) -> 2778 | E22: =SUM(E17:E21) -> 913 | F22: =SUM(F17:F21) -> 3691 | G22: =SUM(G17:G21) -> 34 | H22: =H17 -> 46314 | I22: =I21 -> 46552 | J22: =IF($B$12="","Enter rate",F22*$B$12) -> Enter rate
A23: Check: dev hours here equal the Summary grand total | D23: =IF(D22=Summary!G36,"OK","MISMATCH") -> OK
A25: Scenarios for the client (dev hours, before QA/PM/UAT)
A26: Option | B26: Scope | C26: Dev hours | D26: Build weeks (at current team) | E26: Cost (USD, incl. QA/PM/UAT)
A27: A — Full scope | B27: All 14 features, core + all optional functions | C27: =Summary!F19 -> 2778 | D27: =G22 -> 34 | E27: =IF(C27=0,0,IF($B$12="","Enter rate",(C27*(1+$B$8+$B$9)+$B$10)*$B$12)) -> Enter rate
A28: B — Core first | B28: All 14 features, core functions only (optionals can be added later) | C28: =Summary!D19 -> 1636 | D28: =IF(C28=0,0,ROUNDUP(C28/$B$14,0)+$B$11) -> 20 | E28: =IF(C28=0,0,IF($B$12="","Enter rate",(C28*(1+$B$8+$B$9)+$B$10)*$B$12)) -> Enter rate
A29: C — Wave 1 + 2 only | B29: Sell, buy, change and remember the paint (3, 18, 19, 24–29), selected functions | C29: =D17+D18 -> 1766 | D29: =G17+G18+$B$11 -> 22 | E29: =IF(C29=0,0,IF($B$12="","Enter rate",(C29*(1+$B$8+$B$9)+$B$10)*$B$12)) -> Enter rate
A30: D — Not yet | B30: Pause (0 h, prices held 60 days) or a paid discovery sprint (~40 h: finalise answers, dev-lead review, fixed quote) | C30: =0 -> 0 | D30: =IF(C30=0,0,ROUNDUP(C30/$B$14,0)+$B$11) -> 0 | E30: =IF(C30=0,0,IF($B$12="","Enter rate",(C30*(1+$B$8+$B$9)+$B$10)*$B$12)) -> 0
A31: Build weeks include the UAT window. Weekly Wednesday progress demos run through every wave.

Sheet Hours Breakdown
A1: Estimate Master — Hours Breakdown by Feature
A2: Set Include? to No on any Optional row to see the hours saved. Core rows cannot be removed without breaking the feature.
A4: 3 | B4: Feature 3 — Project-Specific Color Card
A5: Feature | B5: Ref | C5: Functionality | D5: Deliverable | E5: Type | F5: If left out | G5: Hours | H5: Include? | I5: Selected hours
A6: 3 | B6: 3.1 | C6: Colour list and card versions | D6: Job Color Card tab listing each colour with its specifications, state badges and read-only earlier versions | E6: Core | F6: Required. The feature does not work without it. | G6: 32 | H6: Yes | I6: =IF(H6="Yes",G6,0) -> 32
A7: 3 | B7: 3.2 | C7: Specification editor | D7: Form for sheen, coats, primer, coat sequence, surfaces, lifespan default and ordering fields, with all save and approval validations | E7: Core | F7: Required. The feature does not work without it. | G7: 40 | H7: Yes | I7: =IF(H7="Yes",G7,0) -> 40
A8: 3 | B8: 3.3 | C8: Approval and evidence | D8: Send selected specifications for approval, record the customer's reply (including partial approval) and store the evidence; a new version never inherits a signature | E8: Core | F8: Required. The feature does not work without it. | G8: 32 | H8: Yes | I8: =IF(H8="Yes",G8,0) -> 32
A9: 3 | B9: 3.4 | C9: Signed-job change check (Rule 1) | D9: Decides whether a change needs office approval, a Colour Re-approval or a priced change order; flags linked orders and names who calls the store | E9: Core | F9: Required. The feature does not work without it. | G9: 24 | H9: Yes | I9: =IF(H9="Yes",G9,0) -> 24
A10: 3 | B10: 3.5 | C10: Access rules and activity log | D10: Role checks for editing, lifespan locks and completed jobs; every change and blocked attempt logged | E10: Core | F10: Required. The feature does not work without it. | G10: 16 | H10: Yes | I10: =IF(H10="Yes",G10,0) -> 16
A11: 3 | B11: 3.6 | C11: Custom sample tracker | D11: Sample rounds with date, deliverer, outcome and photo; rejected rounds kept permanently | E11: Optional | F11: Custom colour matches are tracked outside the system. The colour stays in draft until someone approves it manually. | G11: 20 | H11: Yes | I11: =IF(H11="Yes",G11,0) -> 20
A12: 3 | B12: 3.7 | C12: Crew card and customer card printouts | D12: Two print/PDF layouts: crew card by room, customer card with swatch, name, sheen and location only | E12: Optional | F12: Crew and customer read the card on screen. No paper copy is produced. | G12: 16 | H12: Yes | I12: =IF(H12="Yes",G12,0) -> 16
A13: 3 | B13: 3.8 | C13: CSV export of specifications | D13: One-click CSV of the specification list | E13: Optional | F13: No spreadsheet export. Data stays viewable on screen. | G13: 4 | H13: Yes | I13: =IF(H13="Yes",G13,0) -> 4
A14: 3 | B14: 3.9 | C14: Two-editor conflict check | D14: The second conflicting save fails with a reload prompt instead of overwriting the first | E14: Optional | F14: The last save wins. Low risk for a small team, but one person's edit can be overwritten. | G14: 8 | H14: Yes | I14: =IF(H14="Yes",G14,0) -> 8
C15: Core hours (required) | G15: =SUMIFS(G6:G14,E6:E14,"Core") -> 144
C16: Optional hours (full list) | G16: =SUMIFS(G6:G14,E6:E14,"Optional") -> 48
C17: Selected hours for this feature | I17: =SUM(I6:I14) -> 192
A19: 18 | B19: Feature 18 — Material Calculation And Order Generation
A20: Feature | B20: Ref | C20: Functionality | D20: Deliverable | E20: Type | F20: If left out | G20: Hours | H20: Include? | I20: Selected hours
A21: 18 | B21: 18.1 | C21: Demand calculation | D21: Paint and primer need per coat and surface condition, with coverage precedence (override, field rate, manufacturer) shown on screen | E21: Core | F21: Required. The feature does not work without it. | G21: 40 | H21: Yes | I21: =IF(H21="Yes",G21,0) -> 40
A22: 18 | B22: 18.2 | C22: Waste and container packing | D22: Highest-matching waste allowance, rounding once to 3 decimals, packing into available quart / gallon / 5-gallon sizes | E22: Core | F22: Required. The feature does not work without it. | G22: 32 | H22: Yes | I22: =IF(H22="Yes",G22,0) -> 32
A23: 18 | B23: 18.3 | C23: Quantity state panel (Rule 2) | D23: Calculated, sent, acknowledged, received, outstanding and orderable-now figures from one formula | E23: Core | F23: Required. The feature does not work without it. | G23: 24 | H23: Yes | I23: =IF(H23="Yes",G23,0) -> 24
A24: 18 | B24: 18.4 | C24: Purchase order generation and approval | D24: Numbered POs (JOB-PO-01), $1,500 estimator and $3,000 owner limits, double-click protection, prices hidden from estimators, PO PDF | E24: Core | F24: Required. The feature does not work without it. | G24: 40 | H24: Yes | I24: =IF(H24="Yes",G24,0) -> 40
A25: 18 | B25: 18.5 | C25: Receiving and over-receipt routing | D25: Record received quantities; up to 10% over goes to job cost, above that to shelf stock, with office approval | E25: Core | F25: Required. The feature does not work without it. | G25: 24 | H25: Yes | I25: =IF(H25="Yes",G25,0) -> 24
A26: 18 | B26: 18.6 | C26: Leftover shelf stock | D26: Match sealed stock under two years old, physical confirmation, job reservation and transfers between jobs | E26: Optional | F26: All paint is bought new. Leftover paint is tracked outside the system. | G26: 32 | H26: Yes | I26: =IF(H26="Yes",G26,0) -> 32
A27: 18 | B27: 18.7 | C27: Estimator quantity adjustments | D27: ±10% self-approved adjustments with a note; larger or from-zero changes wait for owner or office approval | E27: Optional | F27: Only the office manager or owner can change calculated quantities. | G27: 12 | H27: Yes | I27: =IF(H27="Yes",G27,0) -> 12
A28: 18 | B28: 18.8 | C28: Consumables allowance | D28: Separate allowance line ($35 / $55 per room, $150 + $25 per 1,000 sq ft exterior) | E28: Optional | F28: Consumables are added to orders by hand. | G28: 12 | H28: Yes | I28: =IF(H28="Yes",G28,0) -> 12
A29: 18 | B29: 18.9 | C29: Equipment rental lines | D29: Manual rental rows kept apart from measured demand | E29: Optional | F29: Rentals are ordered and costed outside the system. | G29: 8 | H29: Yes | I29: =IF(H29="Yes",G29,0) -> 8
A30: 18 | B30: 18.10 | C30: Preliminary shopping list | D30: Labelled list for unsigned jobs with no PO number and no supplier submission | E30: Optional | F30: No shopping list until the job is signed. | G30: 12 | H30: Yes | I30: =IF(H30="Yes",G30,0) -> 12
A31: 18 | B31: 18.11 | C31: Changed-since-estimate warning | D31: Warns when coverage or cost changed after approval and shows both figures to permitted roles | E31: Optional | F31: Price or coverage drift is only seen when someone compares manually. | G31: 12 | H31: Yes | I31: =IF(H31="Yes",G31,0) -> 12
A32: 18 | B32: 18.12 | C32: Lowest-price packing option and CSV export | D32: Office can switch packing to lowest price; CSV export with restricted columns | E32: Optional | F32: Packing always uses least leftover. PO is available as PDF only. | G32: 12 | H32: Yes | I32: =IF(H32="Yes",G32,0) -> 12
C33: Core hours (required) | G33: =SUMIFS(G21:G32,E21:E32,"Core") -> 160
C34: Optional hours (full list) | G34: =SUMIFS(G21:G32,E21:E32,"Optional") -> 100
C35: Selected hours for this feature | I35: =SUM(I21:I32) -> 260
A37: 19 | B37: Feature 19 — Supplier Integration
A38: Feature | B38: Ref | C38: Functionality | D38: Deliverable | E38: Type | F38: If left out | G38: Hours | H38: Include? | I38: Selected hours
A39: 19 | B39: 19.1 | C39: Supplier and branch setup | D39: Two Sherwin-Williams branch profiles (name, store no., account no., phone); account numbers restricted | E39: Core | F39: Required. The feature does not work without it. | G39: 16 | H39: Yes | I39: =IF(H39="Yes",G39,0) -> 16
A40: 19 | B40: 19.2 | C40: Order submission with evidence | D40: Deliberate destination confirmation; send by print, email or phone with the required evidence for each channel | E40: Core | F40: Required. The feature does not work without it. | G40: 32 | H40: Yes | I40: =IF(H40="Yes",G40,0) -> 32
A41: 19 | B41: 19.3 | C41: Status tracking per order and line | D41: Sent, Acknowledged, Ready, Picked up, Partially filled, Problem; unfamiliar supplier text kept word for word | E41: Core | F41: Required. The feature does not work without it. | G41: 32 | H41: Yes | I41: =IF(H41="Yes",G41,0) -> 32
A42: 19 | B42: 19.4 | C42: Acknowledgment clock and exception list | D42: 4-working-hour clock (Mon–Fri 7–4, holidays excluded), escalation from sender to office manager to owner | E42: Core | F42: Required. The feature does not work without it. | G42: 24 | H42: Yes | I42: =IF(H42="Yes",G42,0) -> 24
A43: 19 | B43: 19.5 | C43: Product mapping to store item codes | D43: Map products, units and pack sizes to store codes, including colour number and tint formula | E43: Optional | F43: Orders use the readable specification text, which the spec allows for manual orders. | G43: 24 | H43: Yes | I43: =IF(H43="Yes",G43,0) -> 24
A44: 19 | B44: 19.6 | C44: Uncertain-send and resend control | D44: Resend blocked until a branch confirmation call is recorded; original reference kept | E44: Optional | F44: Staff follow a written rule to call the branch before resending. The system does not enforce it. | G44: 12 | H44: Yes | I44: =IF(H44="Yes",G44,0) -> 12
A45: 19 | B45: 19.7 | C45: Delivery date change approvals | D45: Up to 3 days office manager, more than 3 days owner, with original and revised dates recorded | E45: Optional | F45: Date changes are agreed by phone and edited directly. | G45: 12 | H45: Yes | I45: =IF(H45="Yes",G45,0) -> 12
A46: 19 | B46: 19.8 | C46: Replacement and substitution approvals | D46: Rule 1 check plus the 10% line and $200 order-total owner thresholds | E46: Optional | F46: Substitutions are handled by cancelling the line and raising a change order when needed. | G46: 20 | H46: Yes | I46: =IF(H46="Yes",G46,0) -> 20
A47: 19 | B47: 19.9 | C47: Returns and credits | D47: Return untinted product with credit linked to the order and job; tinted paint blocked as non-returnable | E47: Optional | F47: Returns and credits are handled in accounting only. | G47: 20 | H47: Yes | I47: =IF(H47="Yes",G47,0) -> 20
C48: Core hours (required) | G48: =SUMIFS(G39:G47,E39:E47,"Core") -> 104
C49: Optional hours (full list) | G49: =SUMIFS(G39:G47,E39:E47,"Optional") -> 88
C50: Selected hours for this feature | I50: =SUM(I39:I47) -> 192
A52: 21 | B52: Feature 21 — Estimated Versus Actual Performance
A53: Feature | B53: Ref | C53: Functionality | D53: Deliverable | E53: Type | F53: If left out | G53: Hours | H53: Include? | I53: Selected hours
A54: 21 | B54: 21.1 | C54: Filter and period bar | D54: Period, dimension (job, estimator, crew lead, interior/exterior), work-date basis in local timezone | E54: Core | F54: Required. The feature does not work without it. | G54: 16 | H54: Yes | I54: =IF(H54="Yes",G54,0) -> 16
A55: 21 | B55: 21.2 | C55: Comparison grid | D55: Original approved, approved change contribution, revised approved, actual, variance amount and %, Over / Under budget label | E55: Core | F55: Required. The feature does not work without it. | G55: 40 | H55: Yes | I55: =IF(H55="Yes",G55,0) -> 40
A56: 21 | B56: 21.3 | C56: Drill-down and role restrictions | D56: Cost categories allowed for the user's role, linked to source records | E56: Core | F56: Required. The feature does not work without it. | G56: 24 | H56: Yes | I56: =IF(H56="Yes",G56,0) -> 24
A57: 21 | B57: 21.4 | C57: Incomplete jobs and pending hours | D57: Separate grid for incomplete jobs and a pending column kept apart from the main totals | E57: Optional | F57: Only completed jobs appear. Pending hours are not shown. | G57: 12 | H57: Yes | I57: =IF(H57="Yes",G57,0) -> 12
A58: 21 | B58: 21.5 | C58: Variance reason codes | D58: Reason code per row | E58: Optional | F58: Reasons for variance are discussed outside the report. | G58: 8 | H58: Yes | I58: =IF(H58="Yes",G58,0) -> 8
A59: 21 | B59: 21.6 | C59: Saved filters | D59: Save and reuse filter settings | E59: Optional | F59: Filters are set each time. | G59: 8 | H59: Yes | I59: =IF(H59="Yes",G59,0) -> 8
A60: 21 | B60: 21.7 | C60: Issued snapshots | D60: Permanent issued reports that can be found later | E60: Optional | F60: The report is always live. Numbers quoted in a meeting can change later. | G60: 16 | H60: Yes | I60: =IF(H60="Yes",G60,0) -> 16
A61: 21 | B61: 21.8 | C61: Weekly Monday summary | D61: Automatic 7 a.m. Monday summary to owner, office manager and estimating manager | E61: Optional | F61: Managers open the report themselves. | G61: 12 | H61: Yes | I61: =IF(H61="Yes",G61,0) -> 12
A62: 21 | B62: 21.9 | C62: PDF and CSV export | D62: Export of the grid | E62: Optional | F62: Report is viewed on screen only. | G62: 8 | H62: Yes | I62: =IF(H62="Yes",G62,0) -> 8
C63: Core hours (required) | G63: =SUMIFS(G54:G62,E54:E62,"Core") -> 80
C64: Optional hours (full list) | G64: =SUMIFS(G54:G62,E54:E62,"Optional") -> 64
C65: Selected hours for this feature | I65: =SUM(I54:I62) -> 144
A67: 22 | B67: Feature 22 — Employee Hours And Payroll
A68: Feature | B68: Ref | C68: Functionality | D68: Deliverable | E68: Type | F68: If left out | G68: Hours | H68: Include? | I68: Selected hours
A69: 22 | B69: 22.1 | C69: Mobile clock | D69: Crew lead clocks crew in and out per job, job changes, lunch deduction and rounding rule | E69: Core | F69: Required. The feature does not work without it. | G69: 48 | H69: Yes | I69: =IF(H69="Yes",G69,0) -> 48
A70: 22 | B70: 22.2 | C70: Offline punches and conflict flags | D70: Punches queue with no signal and sync later; duplicates, missing time and conflicts flagged | E70: Core | F70: Required. The feature does not work without it. | G70: 40 | H70: Yes | I70: =IF(H70="Yes",G70,0) -> 40
A71: 22 | B71: 22.3 | C71: Timesheet review and approval | D71: Office grid per employee per day; approval with no self-approval | E71: Core | F71: Required. The feature does not work without it. | G71: 32 | H71: Yes | I71: =IF(H71="Yes",G71,0) -> 32
A72: 22 | B72: 22.4 | C72: Export batch to Gusto | D72: Batch locks its entries; approved-time CSV in the bookkeeper's Gusto mapping; double-payment protection | E72: Core | F72: Required. The feature does not work without it. | G72: 32 | H72: Yes | I72: =IF(H72="Yes",G72,0) -> 32
A73: 22 | B73: 22.5 | C73: Labour cost entry and job allocation (Rule 3) | D73: Bookkeeper enters cost totals per employee per period; allocated to jobs by approved hours; remainders by Rule 5 | E73: Core | F73: Required. The feature does not work without it. | G73: 32 | H73: Yes | I73: =IF(H73="Yes",G73,0) -> 32
A74: 22 | B74: 22.6 | C74: Employee attestation and disputes | D74: Employee attests own day; dispute routing with deadlines | E74: Optional | F74: Office approves without employee sign-off. Disputes are handled by phone. Check the state work-rule register first. | G74: 20 | H74: Yes | I74: =IF(H74="Yes",G74,0) -> 20
A75: 22 | B75: 22.7 | C75: Activity codes | D75: Travel, shop, setup, training and rained-out time codes | E75: Optional | F75: All time is recorded as job time. | G75: 8 | H75: Yes | I75: =IF(H75="Yes",G75,0) -> 8
A76: 22 | B76: 22.8 | C76: Location capture | D76: Location on punch with a denied-location flag | E76: Optional | F76: No location evidence on punches. | G76: 12 | H76: Yes | I76: =IF(H76="Yes",G76,0) -> 12
A77: 22 | B77: 22.9 | C77: Mileage claims | D77: Evidence-backed mileage at the current IRS rate | E77: Optional | F77: Mileage is claimed through the existing expense process. | G77: 16 | H77: Yes | I77: =IF(H77="Yes",G77,0) -> 16
A78: 22 | B78: 22.10 | C78: Provider results and correction batches | D78: Per-employee Gusto results; rejected lines corrected into a new small batch | E78: Optional | F78: Rejected lines are fixed directly in Gusto. | G78: 16 | H78: Yes | I78: =IF(H78="Yes",G78,0) -> 16
C79: Core hours (required) | G79: =SUMIFS(G69:G78,E69:E78,"Core") -> 184
C80: Optional hours (full list) | G80: =SUMIFS(G69:G78,E69:E78,"Optional") -> 72
C81: Selected hours for this feature | I81: =SUM(I69:I78) -> 256
A83: 24 | B83: Feature 24 — Change Orders And Additional Work
A84: Feature | B84: Ref | C84: Functionality | D84: Deliverable | E84: Type | F84: If left out | G84: Hours | H84: Include? | I84: Selected hours
A85: 24 | B85: 24.1 | C85: Change order builder and pricing | D85: Six change types; incremental lines only; original markup, tax rate on the CO date, half-up rounding | E85: Core | F85: Required. The feature does not work without it. | G85: 48 | H85: Yes | I85: =IF(H85="Yes",G85,0) -> 48
A86: 24 | B86: 24.2 | C86: Internal approval | D86: Owner approves gross additions over $2,000 and every credit; no inherited discount without owner | E86: Core | F86: Required. The feature does not work without it. | G86: 16 | H86: Yes | I86: =IF(H86="Yes",G86,0) -> 16
A87: 24 | B87: 24.3 | C87: Customer approval | D87: Recipient checked against the customer record, person-triggered send, whole-CO approve or reject with signer and evidence | E87: Core | F87: Required. The feature does not work without it. | G87: 32 | H87: Yes | I87: =IF(H87="Yes",G87,0) -> 32
A88: 24 | B88: 24.4 | C88: Downstream updates and billing | D88: Work order, material demand, scheduler task and billing action; supplemental invoices and credit notes | E88: Core | F88: Required. The feature does not work without it. | G88: 40 | H88: Yes | I88: =IF(H88="Yes",G88,0) -> 40
A89: 24 | B89: 24.5 | C89: Approval links with expiry | D89: 30-day links, superseded links blocked with an explanation, new link when the signer changes | E89: Optional | F89: Change orders are sent as a PDF by email and the written reply is stored as evidence. | G89: 12 | H89: Yes | I89: =IF(H89="Yes",G89,0) -> 12
A90: 24 | B90: 24.6 | C90: Parent and child change orders | D90: Child can be drafted but not sent until the parent is resolved; repriced if parent rejected | E90: Optional | F90: Staff wait for one change order to resolve before drafting the next. | G90: 16 | H90: Yes | I90: =IF(H90="Yes",G90,0) -> 16
A91: 24 | B91: 24.7 | C91: Emergency work | D91: Verbal approval under $500 with photos, findings, authoriser, 2-working-day confirmation and escalation | E91: Optional | F91: No emergency path. All work waits for written approval. | G91: 20 | H91: Yes | I91: =IF(H91="Yes",G91,0) -> 20
A92: 24 | B92: 24.8 | C92: Disputed work and refunds | D92: Disputed state referred to owner; account credit by default, 14-day refund window | E92: Optional | F92: Disputes and refunds are handled outside the system. | G92: 16 | H92: Yes | I92: =IF(H92="Yes",G92,0) -> 16
A93: 24 | B93: 24.9 | C93: Deposit review trigger | D93: Flags when signed net changes exceed 25% of the original contract; revised deposit target | E93: Optional | F93: Office checks deposits manually on large changes. | G93: 8 | H93: Yes | I93: =IF(H93="Yes",G93,0) -> 8
A94: 24 | B94: 24.10 | C94: Daily exception list and retry | D94: 7 a.m. list of failed downstream actions with retry of missing actions only | E94: Optional | F94: Failed updates are found by checking each change order. | G94: 12 | H94: Yes | I94: =IF(H94="Yes",G94,0) -> 12
A95: 24 | B95: 24.11 | C95: Customer presentation and print | D95: Customer view of the change and revised total; printable document | E95: Optional | F95: Customer sees the emailed PDF only. | G95: 12 | H95: Yes | I95: =IF(H95="Yes",G95,0) -> 12
C96: Core hours (required) | G96: =SUMIFS(G85:G95,E85:E95,"Core") -> 136
C97: Optional hours (full list) | G97: =SUMIFS(G85:G95,E85:E95,"Optional") -> 96
C98: Selected hours for this feature | I98: =SUM(I85:I95) -> 232
A100: 25 | B100: Feature 25 — Historical Property Paint Record
A101: Feature | B101: Ref | C101: Functionality | D101: Deliverable | E101: Type | F101: If left out | G101: Hours | H101: Include? | I101: Selected hours
A102: 25 | B102: 25.1 | C102: Property structure and surface tree | D102: Stable property ID; building / unit, room or elevation, surface; address fixes never detach jobs | E102: Core | F102: Required. The feature does not work without it. | G102: 32 | H102: Yes | I102: =IF(H102="Yes",G102,0) -> 32
A103: 25 | B103: 25.2 | C103: Closeout confirmation | D103: Crew lead confirms colour, sheen, coats and completion date per surface; office closes the job; missing actuals labelled Not recorded | E103: Core | F103: Required. The feature does not work without it. | G103: 32 | H103: Yes | I103: =IF(H103="Yes",G103,0) -> 32
A104: 25 | B104: 25.3 | C104: Application timeline | D104: Newest-first history per surface with Confirmed / Unverified badges; touch-ups logged on the same application | E104: Core | F104: Required. The feature does not work without it. | G104: 24 | H104: Yes | I104: =IF(H104="Yes",G104,0) -> 24
A105: 25 | B105: 25.4 | C105: Post-close corrections | D105: Owner or office manager corrections with old value, new value, author, date and reason | E105: Core | F105: Required. The feature does not work without it. | G105: 16 | H105: Yes | I105: =IF(H105="Yes",G105,0) -> 16
A106: 25 | B106: 25.5 | C106: Search, staff view and customer view | D106: Search by address, customer or colour; hours and costs staff-only | E106: Core | F106: Required. The feature does not work without it. | G106: 24 | H106: Yes | I106: =IF(H106="Yes",G106,0) -> 24
A107: 25 | B107: 25.6 | C107: Correction notices to the customer | D107: Notice when colour, product, sheen, coats or location changes; a person presses send | E107: Optional | F107: Customers are not told about corrections. | G107: 8 | H107: Yes | I107: =IF(H107="Yes",G107,0) -> 8
...

Sheet Notes
A1: Estimate basis and assumptions
A3: Source | B3: EMTS User Stories and Final Design v1.0 (23 September 2026). Each row maps to a component or rule in that document; Ref numbers follow its component numbers where they exist.
A4: What the hours include | B4: Production build in the live Estimate Master app (Next.js): data model and API, screens, validations, access rules, activity logging, unit tests, and developer testing for that function.
A5: What the hours exclude | B5: Project management, client meetings, UAT rounds, deployment, and time waiting on launch-gate inputs from the client (see the design document's Launch Gates section).
A6: Outside systems | B6: Gusto (22), QuickBooks Online (33) and Meta / Facebook / Instagram (34) hours assume their APIs or CSV formats behave as documented. Account approval and access problems on the provider side are not included.
A7: Accuracy | B7: Planning estimates. Expect a range of about ±20% per feature until the development team reviews each row.
A8: Existing prototype | B8: Features 3, 18, 19, 24, 25, 26, 27, 28 and 29 are in the clickable prototype. It speeds up the production build as a reference, but these hours assume the production code is written fresh in the real app.
A9: Input cells | B9: Hours (blue text) and Include? (yellow cells) can be edited. Everything else is calculated.
A10: Prepared by | B10: AbroadWorks project management, for client review.
A1001: Hours filled | B1001: 30 September 2026 by project management as planning estimates. Development lead to review each row before the figures are quoted as a fixed price.
A1002: Existing prototype | B1002: As of 30 September 2026 all 14 features, plus parts of sections 16, 17 and 20, are in the clickable prototype. The hours still assume production code is written fresh in the live app.
A1003: Add-ons | B1003: Sections 15, 16, 17 and 20 of the patent document are not in the 14 selected features. They are listed separately, switched off by default, and need client confirmation (and a check of what the live Phase 1 scheduler already does).
